{
    "code": 0,
    "data": {
        "album": "baozou",
        "name": "暴走大事件第五季",
        "video": [{"id":"501","name":"【暴走大事件第五季】01 王尼玛搬新家恶补春节热点","cid":"14024054"},{"id":"502","name":"【暴走大事件第五季】02 大事件吉祥物遭遇空前危机，东莞之歌祭奠那逝去的青春","cid":"14262771"},{"id":"503","name":"【暴走大事件第五季】03 暴走2017奥斯长颁奖盛典","cid":"14504857"},{"id":"504","name":"【暴走大事件第五季】04 尴尬气质偶像的自我救赎，国际大佬开启狼人杀大战","cid":"27451137"},{"id":"505","name":"【暴走大事件第五季】05 王尼玛爆款直播拔剑小学生市场，韩国开启作妖新篇章","cid":"14977165"},{"id":"506","name":"【暴走大事件第五季】06 王尼玛绿色教材领跑儿童性教育启蒙","cid":"15213955"},{"id":"507","name":"【暴走大事件第五季】07 老虎伤人的最根本解决办法，90后晚年生活多领域畅想","cid":"15452837"},{"id":"508","name":"【暴走大事件第五季】08 张全蛋旅馆惊魂血战失足女","cid":"15697008"},{"id":"509","name":"【暴走大事件第五季】09 大事件特别篇 感性和理性的正面博弈","cid":"27451546"},{"id":"510","name":"【暴走大事件第五季】10 红鼻子节开启全民公益之夏，爱与正义完美化解医患矛盾","cid":"16248603"},{"id":"511","name":"【暴走大事件第五季】11 《同学的名义》揭秘校园潜规则，大队长骑行受创刮蛋疗伤","cid":"18683680"},{"id":"512","name":"【暴走大事件第五季】12 王尼玛发布《谷拜单身》APP，共享经济改变单身命运","cid":"16759723"},{"id":"513","name":"【暴走大事件第五季】13 终于来了！3亿青少年儿童必备神器《滴滴专掐》震撼发布","cid":"17044907"},{"id":"514","name":"【暴走大事件第五季】14 王大锤正在呼叫你……白客化身客服连线暴走家族被玩坏","cid":"17322254"},{"id":"515","name":"【暴走大事件第五季】15 急招！暴走人事部启动一级人才战略储备","cid":"17589436"},{"id":"516","name":"【暴走大事件第五季】16 富有者联盟之罪恶都市的救赎","cid":"17864285"},{"id":"517","name":"【暴走大事件第五季】17 暴走大事件六一特别篇","cid":"27453916"},{"id":"518","name":"【暴走大事件第五季】18 琼瑶已被气哭！木子化身紫薇花样演绎还珠格格","cid":"27453991"},{"id":"519","name":"【暴走大事件第五季】19 张全蛋做客深夜食堂曝光隐藏恋情","cid":"19082848"},{"id":"520","name":"【暴走大事件第五季】20 王尼玛教你即兴freestyle，大队长领衔小学生酒桌文化","cid":"19392570"},{"id":"521","name":"【暴走大事件第五季】21 千万单身汪都在用的三分钟把妹攻略","cid":"19736243"},{"id":"522","name":"【暴走大事件第五季】22 扎心街访之小学生和王者荣耀，卖火锅的小女孩走进童话版深夜食堂","cid":"27453970"},{"id":"523","name":"【暴走大事件第五季】23 凶宅避暑开启纳凉新篇章，暴走催债APP一键根除老赖","cid":"20434938"},{"id":"524","name":"【暴走大事件第五季】24 《圣母之歌》教你一分钟鉴婊，公车泰迪的花式解决办法","cid":"21030324"},{"id":"525","name":"【暴走大事件第五季】25 漫威英雄征战中国受重挫，大力哥弃恶从善加盟睡前故事","cid":"21244900"},{"id":"526","name":"【暴走大事件第五季】26 喜羊羊热血式包装叫板战狼2","cid":"21674092"},{"id":"527","name":"【暴走大事件第五季】27 暴走夏令营一招制敌根除网瘾，云对象彻底解放双手告别单身","cid":"27455378"},{"id":"528","name":"【暴走大事件第五季】28 《暴走说法》走进撸猫成瘾少年的世界","cid":"22541773"},{"id":"529","name":"【暴走大事件第五季】29 9月不撸吹响战斗号角，互联网上演教育圈小时代","cid":"23120128"},{"id":"530","name":"【暴走大事件第五季】30 王尼玛土味小视频带你体验放肆爱情","cid":"27455266"},{"id":"531","name":"【暴走大事件第五季】31 张全蛋质检新章用爱解锁iphoneX","cid":"27455454"},{"id":"532","name":"【暴走大事件第五季】32 纸巾化身中国版教父分分钟主持公道","cid":"27455391"},{"id":"533","name":"【暴走大事件第五季】33 王尼玛紧急发布长假脱坑指南，神秘大咖为爱唱响九月不撸","cid":"24248551"},{"id":"534","name":"【暴走大事件第五季】34 暴走新摇滚扎心诠释中年危机","cid":"27455357"},{"id":"535","name":"【暴走大事件第五季】35大队长《校园有穷逼》螺旋走位巧夺助学金","cid":"27455530"},{"id":"536","name":"【暴走大事件第五季】36 女版绝地求生秘籍助你大吉大利","cid":"27449839"},{"id":"537","name":"【暴走大事件第五季】37外卖三大势力决战光明顶，土味视频迈入高雅殿堂","cid":"27452602"},{"id":"538","name":"【暴走大事件第五季】38 阿里巴巴与四十大盗方言新篇，木子全蛋灵魂演技翻拍你的名字","cid":"27845499"},{"id":"539","name":"【暴走大事件第五季】39 王尼玛机智化解婚闹危机圆梦新人"},{"id":"540","name":"【暴走大事件第五季】40 土味视频迈入新纪元，男德教育打造好男标准","cid":"28547920"},{"id":"541","name":"【暴走大事件第五季】41【正在录播】暴走超大事件跨年狂欢，王尼玛携手豪华阵容挥手","cid":"29017116"},{"id":"542","name":"【暴走大事件第五季】42【暴走嗦法】怵目惊心！暗访直男地下培训基地","cid":"29730375"},{"id":"543","name":"【暴走大事件第五季】43 感动网友2017年度颁奖盛典","cid":"30114803"},{"id":"544","name":"【暴走大事件第五季】44 酒局神器助你春节千杯不倒，氪金少女的中年男人养成记","cid":"30548313"},{"id":"545","name":"【暴走大事件第五季】45 旅行青蛙外出真相感动网友，赶尸创业揭秘致富骗局","cid":"31019027"},{"id":"546","name":"【暴走大事件第五季】46《动物世界》之候鸟春劫篇；春晚预告片燃起年度大戏","cid":"31531338"},{"id":"547","name":"【暴走大事件第五季】47 铁柱暗访泡妞培训班揭秘渣男约炮全套流程，王尼玛盘点那些年体育大赛中韩国奥运精神","cid":"33593131"},{"id":"548","name":"【暴走大事件第五季】48 《绝地求爱》演绎三毛荷西的放肆爱情"},{"id":"549","name":"【暴走大事件第五季】49 尼玛睡前正能量之《丑烤鸭的故事》","cid":"34603623"},{"id":"550","name":"【暴走大事件第五季】50 远离键盘侠，赵铁柱亲授如何降服杠精","cid":"35190692"},{"id":"551","name":"【暴走大事件第五季】51 警惕！你的隐私正在被泄漏…","cid":"36318603"},{"id":"552","name":"【暴走大事件第五季】52  暴走大事件邀请你加入中国头号玩家","cid":"36928801"},{"id":"553","name":"【暴走大事件第五季】53 预告片全球首播，暴走漫画这次真的要做大电影了","cid":"37542662"},{"id":"554","name":"【暴走大事件第五季】54 你真的了解抑郁症吗？","cid":"38140577"},{"id":"555","name":"【暴走大事件第五季】55 滴滴外卖美团外卖城市决战，不到一炷香时间竟两败俱伤；如何拍一部中国版的头号玩家，大事件燃烧经费燃爆你的青春；人人自危的时代，你每天是否","cid":"38761131"}]
    }
}